[{"rating":["8.7","45"],"rank":1,"cover_url":"https://img3.doubanio.com\/view\/photo\/s_ratio_poster\/public\/p1119483806.jpg","is_playable":true,"id":"1298733","types":["剧情","黑色电影"],"regions":["美国"],"title":"日落大道","url":"https:\/\/movie.douban.com\/subject\/1298733\/","release_date":"1950-08-10","actor_count":10,"vote_count":31061,"score":"8.7","actors":["威廉·霍尔登","葛洛丽亚·斯旺森","埃里克·冯·施特罗海姆","南希·奥尔森","弗雷德·克拉克","巴斯特·基顿","杰克·韦伯","安娜·Q·尼尔松","赫达·霍珀","塞西尔·B·戴米尔"],"is_watched":false},{"rating":["8.7","45"],"rank":2,"cover_url":"https://img3.doubanio.com\/view\/photo\/s_ratio_poster\/public\/p2171823995.jpg","is_playable":true,"id":"1293841","types":["剧情","黑色电影"],"regions":["美国"],"title":"倒扣的王牌","url":"https:\/\/movie.douban.com\/subject\/1293841\/","release_date":"1951-06-29","actor_count":7,"vote_count":6859,"score":"8.7","actors":["柯克·道格拉斯","简·斯特林","罗伯特·亚瑟","波特·霍尔","雷·蒂尔","理查德·贝内迪克特","杰拉尔丁·豪尔"],"is_watched":false},{"rating":["8.6","45"],"rank":3,"cover_url":"https://img3.doubanio.com\/view\/photo\/s_ratio_poster\/public\/p2192213954.jpg","is_playable":false,"id":"1293936","types":["犯罪","黑色电影","惊悚"],"regions":["美国"],"title":"杀手","url":"https:\/\/movie.douban.com\/subject\/1293936\/","release_date":"1956-06-06","actor_count":6,"vote_count":10266,"score":"8.6","actors":["斯特林·海登","小伊莱莎·库克","文斯·爱德华兹","杰伊·C·弗利朋","玛丽·温莎","柯琳·格蕾"],"is_watched":false},{"rating":["8.5","45"],"rank":4,"cover_url":"https://img3.doubanio.com\/view\/photo\/s_ratio_poster\/public\/p1675680930.jpg","is_playable":true,"id":"1293226","types":["犯罪","黑色电影","惊悚"],"regions":["美国"],"title":"双重赔偿","url":"https:\/\/movie.douban.com\/subject\/1293226\/","release_date":"1944-07-03","actor_count":7,"vote_count":19368,"score":"8.5","actors":["弗莱德·麦克莫瑞","芭芭拉·斯坦威克","爱德华·罗宾逊","波特·霍尔","福图尼奥·博纳诺瓦","汤姆·鲍尔斯","琼·希瑟"],"is_watched":false},{"rating":["8.4","45"],"rank":5,"cover_url":"https://img3.doubanio.com\/view\/photo\/s_ratio_poster\/public\/p2201821222.jpg","is_playable":false,"id":"1301216","types":["剧情","犯罪","惊悚","黑色电影"],"regions":["美国"],"title":"歼匪喋血战","url":"https:\/\/movie.douban.com\/subject\/1301216\/","release_date":"1949-09-02","actor_count":57,"vote_count":999,"score":"8.4","actors":["詹姆斯·卡格尼","弗吉尼亚·梅奥","艾德蒙·奥布莱恩","玛格丽特·威彻利","史蒂夫·柯臣","Jim Toney","Jack Perrin","Eddie Phillips","Terry O'Sullivan","Larry McGrath","Fern Eggen","Art Miles","约翰·麦圭尔","Murray Leonard","希德梅尔顿","雷·蒙哥马利","Nolan Leary","李·费尔普斯","John Pickard","George Taylor","Harry Strang","Jim Thorpe","福特·雷尼","杰弗里·塞尔","格兰丁·罗德","Milton Parsons","Ralph Volkie","Joey Ray","George Spaulding","罗伯特·奥斯特洛","Perry Ivins","Colin Kenny","沃利·卡斯尔","Claudia Barrett","Ray Bennett","Paul Guilfoyle","约翰·阿彻尔","卡尔·哈博","赫歇尔·多尔蒂","米基·诺克斯","伊恩·麦克唐纳","弗雷德·克拉克","Tom Coleman","约翰·巴特勒","哈里·劳特","DeForrest Lawrence","Sherry Hall","Buddy Gorman","Robert Foulk","Art Foster","Eddie Foster","Robert Carson","Leo Cleary","马歇尔·布拉德福德","Bill Cartledge","Fred Coby","G·帕特·柯林斯"],"is_watched":false},{"rating":["8.4","45"],"rank":6,"cover_url":"https://img3.doubanio.com\/view\/photo\/s_ratio_poster\/public\/p2163627296.jpg","is_playable":false,"id":"1294978","types":["剧情","犯罪","惊悚","黑色电影"],"regions":["美国"],"title":"私枭血","url":"https:\/\/movie.douban.com\/subject\/1294978\/","release_date":"1939-10-23","actor_count":12,"vote_count":682,"score":"8.4","actors":["詹姆斯·卡格尼","普瑞丝西拉·兰恩","亨弗莱·鲍嘉","格拉黛丝·乔治","杰弗瑞·林恩","弗兰克·麦休","保罗·凯利","伊丽莎白·里斯登","爱德华·基恩","乔·索耶","约瑟夫·奎汉","乔治·米克"],"is_watched":false},{"rating":["8.4","45"],"rank":7,"cover_url":"https://img1.doubanio.com\/view\/photo\/s_ratio_poster\/public\/p2195717708.jpg","is_playable":false,"id":"1292471","types":["剧情","犯罪","黑色电影"],"regions":["美国"],"title":"亡命者","url":"https:\/\/movie.douban.com\/subject\/1292471\/","release_date":"1932-11-19","actor_count":5,"vote_count":528,"score":"8.4","actors":["保罗·穆尼","格伦达·法瑞尔","海伦·文逊","诺埃尔·弗朗西斯","普雷斯顿·福斯特"],"is_watched":false},{"rating":["8.3","45"],"rank":8,"cover_url":"https://img1.doubanio.com\/view\/photo\/s_ratio_poster\/public\/p1884306259.jpg","is_playable":true,"id":"1293973","types":["黑色电影","悬疑","爱情","惊悚"],"regions":["美国"],"title":"爱德华大夫","url":"https:\/\/movie.douban.com\/subject\/1293973\/","release_date":"1945-12-28","actor_count":7,"vote_count":31873,"score":"8.3","actors":["英格丽·褒曼","格利高里·派克","迈克尔·契诃夫","里奥.G.卡罗尔","朗达·弗莱明","里吉斯·图米","童自荣"],"is_watched":false},{"rating":["8.3","45"],"rank":9,"cover_url":"https://img3.doubanio.com\/view\/photo\/s_ratio_poster\/public\/p935420710.jpg","is_playable":true,"id":"1293381","types":["剧情","犯罪","惊悚","黑色电影"],"regions":["德国"],"title":"M就是凶手","url":"https:\/\/movie.douban.com\/subject\/1293381\/","release_date":"1931-05-11","actor_count":16,"vote_count":19821,"score":"8.3","actors":["彼得·洛","艾伦·维德曼","因格·兰德特","奥托·维尔尼克","西奥·林根","弗朗茨·斯坦","厄恩斯特·斯塔尔-纳什布拉","格哈德·比纳特","卡尔·普拉滕","罗莎·法蕾雅","鲍尔·肯培","弗里茨·奥德玛","弗里德里希·纳森","格林德根斯·古斯塔法","西奥多·卢斯","赫塔·瓦尔特"],"is_watched":false},{"rating":["8.3","45"],"rank":10,"cover_url":"https://img3.doubanio.com\/view\/photo\/s_ratio_poster\/public\/p2193745066.jpg","is_playable":true,"id":"1295451","types":["黑色电影","悬疑","惊悚"],"regions":["英国"],"title":"第三人","url":"https:\/\/movie.douban.com\/subject\/1295451\/","release_date":"1949-09-03","actor_count":10,"vote_count":13457,"score":"8.3","actors":["约瑟夫·科顿","阿莉达·瓦利","奥逊·威尔斯","特瑞沃·霍华德","伯纳德·李","Hedwig Bleibtreu","Erich Ponto","Siegfried Breuer","厄恩斯特·多伊奇","保罗·赫尔比格尔"],"is_watched":false}]